google/cloud/visionai/__init__.py
google/cloud/visionai/gapic_version.py
google/cloud/visionai/py.typed
google/cloud/visionai_v1/__init__.py
google/cloud/visionai_v1/gapic_metadata.json
google/cloud/visionai_v1/gapic_version.py
google/cloud/visionai_v1/py.typed
google/cloud/visionai_v1/services/__init__.py
google/cloud/visionai_v1/services/app_platform/__init__.py
google/cloud/visionai_v1/services/app_platform/async_client.py
google/cloud/visionai_v1/services/app_platform/client.py
google/cloud/visionai_v1/services/app_platform/pagers.py
google/cloud/visionai_v1/services/app_platform/transports/__init__.py
google/cloud/visionai_v1/services/app_platform/transports/base.py
google/cloud/visionai_v1/services/app_platform/transports/grpc.py
google/cloud/visionai_v1/services/app_platform/transports/grpc_asyncio.py
google/cloud/visionai_v1/services/app_platform/transports/rest.py
google/cloud/visionai_v1/services/app_platform/transports/rest_base.py
google/cloud/visionai_v1/services/health_check_service/__init__.py
google/cloud/visionai_v1/services/health_check_service/async_client.py
google/cloud/visionai_v1/services/health_check_service/client.py
google/cloud/visionai_v1/services/health_check_service/transports/__init__.py
google/cloud/visionai_v1/services/health_check_service/transports/base.py
google/cloud/visionai_v1/services/health_check_service/transports/grpc.py
google/cloud/visionai_v1/services/health_check_service/transports/grpc_asyncio.py
google/cloud/visionai_v1/services/health_check_service/transports/rest.py
google/cloud/visionai_v1/services/health_check_service/transports/rest_base.py
google/cloud/visionai_v1/services/live_video_analytics/__init__.py
google/cloud/visionai_v1/services/live_video_analytics/async_client.py
google/cloud/visionai_v1/services/live_video_analytics/client.py
google/cloud/visionai_v1/services/live_video_analytics/pagers.py
google/cloud/visionai_v1/services/live_video_analytics/transports/__init__.py
google_cloud_visionai-0.3.0.dist-info/licenses/LICENSE
google_cloud_visionai-0.3.0.dist-info/METADATA
google_cloud_visionai-0.3.0.dist-info/WHEEL
google_cloud_visionai-0.3.0.dist-info/top_level.txt
google_cloud_visionai-0.3.0.dist-info/RECORD
